{
  "genericHttp": {
    "mcpServers": {
      "openmemory": {
        "transport": "http",
        "url": "https://openmemory-mcp-8gnp.onrender.com/mcp"
      }
    }
  },
  "genericStreamableHttp": {
    "mcpServers": {
      "openmemory": {
        "transport": "streamable-http",
        "url": "https://openmemory-mcp-8gnp.onrender.com/mcp"
      }
    }
  },
  "localFallback": {
    "mcpServers": {
      "openmemory": {
        "command": "npx",
        "args": ["-y", "openmemory-mcp"]
      }
    }
  }
}
